forecasting_sandbox/__init__.py
forecasting_sandbox/benchmark_forecast/__init__.py
forecasting_sandbox/benchmark_forecast/benchmark_forecast.py
forecasting_sandbox/fsprophet/__init__.py
forecasting_sandbox/fsprophet/fsprophet.py
forecasting_sandbox/theta/__init__.py
forecasting_sandbox/theta/theta.py
forecasting_sandbox/utils/__init__.py
forecasting_sandbox/utils/multivariate.py
forecasting_sandbox/utils/pred_intervals.py
forecasting_sandbox/utils/tscv_indices.py
forecasting_sandbox/utils/unimultivariate.py
forecasting_sandbox/utils/univariate.py
forecasting_sandbox-0.2.0.dist-info/LICENSE
forecasting_sandbox-0.2.0.dist-info/METADATA
forecasting_sandbox-0.2.0.dist-info/WHEEL
forecasting_sandbox-0.2.0.dist-info/top_level.txt
forecasting_sandbox-0.2.0.dist-info/RECORD
